nv2a_vsh/__about__.py
nv2a_vsh/__init__.py
nv2a_vsh/assemble.py
nv2a_vsh/disassemble.py
nv2a_vsh/grammar/vsh/Vsh.interp
nv2a_vsh/grammar/vsh/Vsh.tokens
nv2a_vsh/grammar/vsh/VshLexer.interp
nv2a_vsh/grammar/vsh/VshLexer.py
nv2a_vsh/grammar/vsh/VshLexer.tokens
nv2a_vsh/grammar/vsh/VshListener.py
nv2a_vsh/grammar/vsh/VshParser.py
nv2a_vsh/grammar/vsh/VshVisitor.py
nv2a_vsh/nv2a_vsh_asm/__init__.py
nv2a_vsh/nv2a_vsh_asm/assembler.py
nv2a_vsh/nv2a_vsh_asm/encoding_error.py
nv2a_vsh/nv2a_vsh_asm/encoding_visitor.py
nv2a_vsh/nv2a_vsh_asm/vsh_encoder.py
nv2a_vsh/nv2a_vsh_asm/vsh_encoder_defs.py
nv2a_vsh/nv2a_vsh_asm/vsh_error_listener.py
nv2a_vsh/nv2a_vsh_asm/vsh_instruction.py
nv2a_vsh-0.1.7.dist-info/METADATA
nv2a_vsh-0.1.7.dist-info/WHEEL
nv2a_vsh-0.1.7.dist-info/entry_points.txt
nv2a_vsh-0.1.7.dist-info/licenses/LICENSE.txt
nv2a_vsh-0.1.7.dist-info/RECORD
