Metadata-Version: 2.4
Name: nv2a-vsh
Version: 0.1.7
Summary: Assembler/disassembler for the Xbox nv2a vertex shader
Project-URL: Documentation, https://github.com/abaire/nv2a_vsh_asm#readme
Project-URL: Issues, https://github.com/abaire/nv2a_vsh_asm/issues
Project-URL: Source, https://github.com/abaire/nv2a_vsh_asm
Author-email: Erik Abair <erik.abair@bearbrains.work>
License-Expression: Unlicense
License-File: LICENSE.txt
Keywords: assembler,nv2a,nvidia,vertex shader,xbox
Classifier: Development Status :: 3 - Alpha
Classifier: Environment :: Console
Classifier: Intended Audience :: Developers
Classifier: Operating System :: OS Independent
Classifier: Programming Language :: Python
Classifier: Programming Language :: Python :: 3.10
Classifier: Programming Language :: Python :: 3.11
Classifier: Programming Language :: Python :: 3.12
Classifier: Topic :: Software Development :: Assemblers
Requires-Python: >=3.10
Requires-Dist: antlr4-python3-runtime~=4.13.2
